[
  {
    "slug": "10-dicas-para-superar-a-ansiedade-e-o-estresse-nos-dias-de-prova-de-concursos-pu",
    "words": [
      "introducao",
      "ansiedade",
      "estresse",
      "sentimentos",
      "comuns",
      "entre",
      "candidatos",
      "preparam",
      "para",
      "concursos",
      "publicos",
      "esses",
      "sentimentos",
      "podem",
      "afetar",
      "negativamente",
      "desempenho",
      "confianca",
      "candidato",
      "tornando",
      "ainda",
      "mais",
      "desafiador",
      "processo",
      "aprovacao",
      "neste",
      "artigo",
      "vamos",
      "explorar",
      "dicas",
      "praticas",
      "para",
      "superar",
      "ansiedade",
      "estresse",
      "dias",
      "prova",
      "concursos",
      "publicos",
      "ajudando",
      "voce",
      "sentir",
      "mais",
      "preparado",
      "confiante",
      "entendendo",
      "ansiedade",
      "estresse",
      "concursos",
      "publicos",
      "antes",
      "mergulharmos",
      "dicas",
      "importante",
      "entender",
      "ansiedade",
      "estresse",
      "comuns",
      "entre",
      "candidatos",
      "pressao",
      "obter",
      "resultado",
      "positivo",
      "competicao",
      "acirrada",
      "incerteza",
      "sobre",
      "proprio",
      "desempenho",
      "podem",
      "criar",
      "ambiente",
      "propicio",
      "para",
      "esses",
      "sentimentos",
      "desenvolvam",
      "ansiedade",
      "pode",
      "manifestar",
      "varias",
      "maneiras",
      "incluindo",
      "preocupacao",
      "excessiva",
      "resultado",
      "prova",
      "dificuldade",
      "para",
      "dormir",
      "manter",
      "sono",
      "nervosismo",
      "agitacao",
      "dificuldade",
      "para",
      "concentrar",
      "estresse",
      "pode",
      "caracterizado",
      "sentimento",
      "sobrecarga",
      "pressao",
      "dificuldade",
      "para",
      "gerenciar",
      "tempo",
      "estudo",
      "eficazmente",
      "perda",
      "motivacao",
      "interesse",
      "pelo",
      "estudo",
      "problemas",
      "saude",
      "como",
      "dores",
      "cabeca",
      "problemas",
      "digestivos",
      "dicas",
      "para",
      "superar",
      "ansiedade",
      "estresse",
      "agora",
      "entendemos",
      "melhor",
      "sinais",
      "sintomas",
      "ansiedade",
      "estresse",
      "vamos",
      "dicas",
      "para",
      "supera",
      "preparacao",
      "mental",
      "preparacao",
      "mental",
      "fundamental",
      "para",
      "lidar",
      "ansiedade",
      "estresse",
      "isso",
      "inclui",
      "tecnicas"
    ]
  },
  {
    "slug": "carreira-de-auditor-fiscal-vale-a-pena",
    "words": [
      "introducao",
      "carreira",
      "auditor",
      "fiscal",
      "escolha",
      "profissional",
      "pode",
      "muito",
      "gratificante",
      "para",
      "aqueles",
      "interesse",
      "financas",
      "contabilidade",
      "direito",
      "neste",
      "artigo",
      "vamos",
      "explorar",
      "carreira",
      "auditor",
      "fiscal",
      "vale",
      "pena",
      "considerando",
      "aspectos",
      "positivos",
      "negativos",
      "oportunidades",
      "desafios",
      "desenvolvimento",
      "auditor",
      "fiscal",
      "auditor",
      "fiscal",
      "profissional",
      "responsavel",
      "verificar",
      "conformidade",
      "empresas",
      "individuos",
      "leis",
      "regulamentacoes",
      "fiscais",
      "eles",
      "trabalham",
      "para",
      "garantir",
      "empresas",
      "individuos",
      "estejam",
      "pagando",
      "impostos",
      "corretos",
      "estejam",
      "sonegando",
      "impostos",
      "cometendo",
      "fraude",
      "fiscal",
      "vantagens",
      "carreira",
      "auditor",
      "fiscal",
      "carreira",
      "auditor",
      "fiscal",
      "oferece",
      "varias",
      "vantagens",
      "incluindo",
      "estabilidade",
      "carreira",
      "auditor",
      "fiscal",
      "considerada",
      "carreira",
      "estavel",
      "pois",
      "governo",
      "sempre",
      "precisara",
      "profissionais",
      "para",
      "verificar",
      "conformidade",
      "fiscal",
      "remuneracao",
      "auditores",
      "fiscais",
      "remunerados",
      "especialmente",
      "aqueles",
      "trabalham",
      "para",
      "governo",
      "para",
      "empresas",
      "grandes",
      "oportunidades",
      "avanco",
      "carreira",
      "auditor",
      "fiscal",
      "oferece",
      "oportunidades",
      "avanco",
      "especialmente",
      "para",
      "aqueles",
      "experiencia",
      "habilidades",
      "areas",
      "como",
      "contabilidade",
      "direito",
      "gestao",
      "diversidade",
      "carreira",
      "auditor",
      "fiscal",
      "diversa",
      "pois",
      "auditores",
      "fiscais",
      "trabalham",
      "diferentes",
      "tipos",
      "empresas",
      "individuos",
      "precisam",
      "conhecimento",
      "diferentes",
      "areas",
      "como",
      "contabilidade",
      "direito",
      "gestao",
      "desafios",
      "carreira",
      "auditor",
      "fiscal",
      "entanto",
      "carreira",
      "auditor",
      "fiscal",
      "tambem",
      "apresenta",
      "desafios",
      "incluindo"
    ]
  },
  {
    "slug": "como-estudar-para-concursos-publicos",
    "words": [
      "introducao",
      "concursos",
      "publicos",
      "excelente",
      "oportunidade",
      "para",
      "quem",
      "busca",
      "carreira",
      "estavel",
      "segura",
      "setor",
      "publico",
      "entanto",
      "concorrencia",
      "intensa",
      "exige",
      "preparacao",
      "cuidadosa",
      "dedicada",
      "neste",
      "artigo",
      "vamos",
      "explorar",
      "como",
      "estudar",
      "para",
      "concursos",
      "publicos",
      "forma",
      "eficaz",
      "abordando",
      "principais",
      "passos",
      "dicas",
      "para",
      "ajuda",
      "alcancar",
      "objetivo",
      "desenvolvimento",
      "defina",
      "seus",
      "objetivos",
      "antes",
      "comecar",
      "estudar",
      "fundamental",
      "definir",
      "quais",
      "concursos",
      "voce",
      "deseja",
      "participar",
      "quais",
      "requisitos",
      "necessarios",
      "para",
      "cada",
      "deles",
      "isso",
      "inclui",
      "verificar",
      "vagas",
      "disponiveis",
      "requisitos",
      "educacao",
      "experiencia",
      "datas",
      "inscricao",
      "realizacao",
      "concurso",
      "faca",
      "plano",
      "estudos",
      "plano",
      "estudos",
      "estruturado",
      "essencial",
      "para",
      "garantir",
      "voce",
      "esteja",
      "estudando",
      "forma",
      "eficaz",
      "isso",
      "inclui",
      "definir",
      "temas",
      "materias",
      "precisam",
      "estudadas",
      "estabelecer",
      "metas",
      "prazos",
      "para",
      "cada",
      "tema",
      "dividir",
      "tempo",
      "estudo",
      "sessoes",
      "regulares",
      "consistentes",
      "utilizar",
      "recursos",
      "estudo",
      "como",
      "livros",
      "cursos",
      "materiais",
      "online",
      "aprenda",
      "gerenciar",
      "tempo",
      "gestao",
      "tempo",
      "fundamental",
      "quando",
      "esta",
      "estudando",
      "para",
      "concursos",
      "publicos",
      "isso",
      "inclui",
      "priorizar",
      "temas",
      "materias",
      "mais",
      "importantes",
      "utilizar",
      "tecnicas",
      "estudo",
      "eficazes",
      "como",
      "tecnica",
      "pomodoro",
      "evitar",
      "distracoes",
      "minimizar",
      "tempo",
      "gasto",
      "atividades",
      "relacionadas",
      "estudo",
      "pratique",
      "simulados",
      "provas",
      "anteriores"
    ]
  },
  {
    "slug": "conhecendo-os-melhores-cursos-gratuitos-para-concursos-publicos",
    "words": [
      "introducao",
      "voce",
      "esta",
      "procurando",
      "oportunidade",
      "carreira",
      "estavel",
      "segura",
      "concursos",
      "publicos",
      "podem",
      "chave",
      "para",
      "sucesso",
      "entanto",
      "preparacao",
      "para",
      "esses",
      "exames",
      "pode",
      "desafiadora",
      "custosa",
      "felizmente",
      "existem",
      "muitos",
      "cursos",
      "gratuitos",
      "para",
      "concursos",
      "publicos",
      "podem",
      "ajuda",
      "preparar",
      "gastar",
      "centavo",
      "neste",
      "artigo",
      "vamos",
      "explorar",
      "melhores",
      "cursos",
      "gratuitos",
      "para",
      "concursos",
      "publicos",
      "fornecer",
      "dicas",
      "praticas",
      "para",
      "ajuda",
      "aproveitar",
      "maximo",
      "esses",
      "recursos",
      "cursos",
      "gratuitos",
      "para",
      "concursos",
      "publicos",
      "cursos",
      "gratuitos",
      "para",
      "concursos",
      "publicos",
      "programas",
      "estudo",
      "online",
      "presenciais",
      "oferecem",
      "materiais",
      "estudo",
      "gratuitos",
      "recursos",
      "educacionais",
      "para",
      "ajudar",
      "candidatos",
      "preparar",
      "para",
      "concursos",
      "publicos",
      "esses",
      "cursos",
      "podem",
      "oferecidos",
      "instituicoes",
      "ensino",
      "orgaos",
      "governamentais",
      "empresas",
      "privadas",
      "geralmente",
      "incluem",
      "aulas",
      "exercicios",
      "simulados",
      "outros",
      "recursos",
      "para",
      "ajudar",
      "candidatos",
      "preparar",
      "para",
      "exames",
      "exemplos",
      "cursos",
      "gratuitos",
      "para",
      "concursos",
      "publicos",
      "aqui",
      "estao",
      "alguns",
      "exemplos",
      "cursos",
      "gratuitos",
      "para",
      "concursos",
      "publicos",
      "voce",
      "pode",
      "considerar",
      "curso",
      "preparacao",
      "para",
      "concursos",
      "publicos",
      "universidade",
      "federal",
      "janeiro",
      "ufrj",
      "esse",
      "curso",
      "oferece",
      "aulas",
      "materiais",
      "estudo",
      "gratuitos",
      "para",
      "ajudar",
      "candidatos",
      "preparar",
      "para",
      "concursos",
      "publicos",
      "areas",
      "como",
      "direito",
      "administracao",
      "engenharia"
    ]
  },
  {
    "slug": "estrategias-de-estudo-eficazes-para-conquistar-vagas-em-concursos-publicos",
    "words": [
      "introducao",
      "preparacao",
      "para",
      "concursos",
      "publicos",
      "desafio",
      "exige",
      "dedicacao",
      "disciplina",
      "estrategia",
      "milhares",
      "candidatos",
      "competindo",
      "vagas",
      "limitadas",
      "fundamental",
      "plano",
      "estudos",
      "definido",
      "para",
      "destacar",
      "neste",
      "artigo",
      "vamos",
      "explorar",
      "estrategias",
      "estudo",
      "mais",
      "eficazes",
      "para",
      "conquistar",
      "vagas",
      "concursos",
      "publicos",
      "transformar",
      "carreira",
      "planejamento",
      "organizacao",
      "plano",
      "estudos",
      "estruturado",
      "fundamental",
      "para",
      "sucesso",
      "concursos",
      "publicos",
      "aqui",
      "estao",
      "algumas",
      "dicas",
      "para",
      "criar",
      "plano",
      "estudos",
      "personalizado",
      "defina",
      "seus",
      "objetivos",
      "antes",
      "comecar",
      "estudar",
      "importante",
      "definir",
      "quais",
      "seus",
      "objetivos",
      "qual",
      "concurso",
      "voce",
      "deseja",
      "conquistar",
      "qual",
      "cargo",
      "voce",
      "deseja",
      "ocupar",
      "faca",
      "levantamento",
      "conteudo",
      "faca",
      "levantamento",
      "todo",
      "conteudo",
      "voce",
      "precisara",
      "estudar",
      "para",
      "concurso",
      "isso",
      "inclui",
      "livros",
      "artigos",
      "videos",
      "outros",
      "recursos",
      "estudo",
      "crie",
      "cronograma",
      "crie",
      "cronograma",
      "estudos",
      "inclua",
      "todos",
      "topicos",
      "voce",
      "precisa",
      "estudar",
      "certifique",
      "incluir",
      "tempo",
      "para",
      "revisao",
      "pratica",
      "exemplo",
      "plano",
      "estudos",
      "aqui",
      "esta",
      "exemplo",
      "plano",
      "estudos",
      "para",
      "concurso",
      "nivel",
      "medio",
      "topico",
      "tempo",
      "estudo",
      "frequencia",
      "portugues",
      "horas",
      "dias",
      "semana",
      "matematica",
      "hora",
      "dias",
      "semana",
      "historia",
      "hora",
      "dias",
      "semana",
      "tecnicas",
      "estudo",
      "alem",
      "plano",
      "estudos",
      "estruturado",
      "importante",
      "utilizar",
      "tecnicas"
    ]
  },
  {
    "slug": "guia-completo-para-entender-e-cumprir-os-prazos-de-inscricao-nos-editais-de-conc",
    "words": [
      "introducao",
      "editais",
      "concursos",
      "publicos",
      "documentos",
      "oficiais",
      "estabelecem",
      "regras",
      "procedimentos",
      "para",
      "realizacao",
      "concurso",
      "publico",
      "eles",
      "contem",
      "informacoes",
      "importantes",
      "como",
      "prazos",
      "inscricao",
      "vagas",
      "disponiveis",
      "requisitos",
      "elegibilidade",
      "criterios",
      "avaliacao",
      "neste",
      "artigo",
      "vamos",
      "explorar",
      "detalhes",
      "prazos",
      "inscricao",
      "editais",
      "concursos",
      "publicos",
      "fornecer",
      "dicas",
      "praticas",
      "para",
      "garantir",
      "voce",
      "cumpra",
      "todos",
      "requisitos",
      "editais",
      "concursos",
      "publicos",
      "editais",
      "concursos",
      "publicos",
      "documentos",
      "oficiais",
      "emitidos",
      "pelas",
      "instituicoes",
      "publicas",
      "responsaveis",
      "realizar",
      "concursos",
      "para",
      "preencher",
      "vagas",
      "diferentes",
      "areas",
      "servico",
      "publico",
      "eles",
      "publicados",
      "jornais",
      "oficiais",
      "sites",
      "governamentais",
      "outras",
      "plataformas",
      "comunicacao",
      "para",
      "informar",
      "interessados",
      "sobre",
      "oportunidades",
      "disponiveis",
      "importancia",
      "editais",
      "concursos",
      "publicos",
      "editais",
      "concursos",
      "publicos",
      "fundamentais",
      "para",
      "garantir",
      "transparencia",
      "equidade",
      "processo",
      "selecao",
      "eles",
      "fornecem",
      "informacoes",
      "detalhadas",
      "sobre",
      "vagas",
      "disponiveis",
      "requisitos",
      "elegibilidade",
      "criterios",
      "avaliacao",
      "prazos",
      "inscricao",
      "alem",
      "disso",
      "editais",
      "tambem",
      "estabelecem",
      "regras",
      "para",
      "realizacao",
      "concurso",
      "incluindo",
      "data",
      "hora",
      "prova",
      "local",
      "realizacao",
      "procedimentos",
      "para",
      "correcao",
      "provas",
      "prazos",
      "inscricao",
      "editais",
      "concursos",
      "publicos",
      "prazos",
      "inscricao",
      "aspectos",
      "mais",
      "importantes",
      "editais",
      "concursos",
      "publicos",
      "eles",
      "determinam",
      "periodo",
      "durante",
      "qual",
      "interessados",
      "podem",
      "inscrever",
      "para"
    ]
  },
  {
    "slug": "carreira-de-auditor-fiscal-salario-e-perspectivas",
    "words": [
      "introducao",
      "carreira",
      "auditor",
      "fiscal",
      "mais",
      "procuradas",
      "respeitadas",
      "brasil",
      "devido",
      "alto",
      "nivel",
      "estabilidade",
      "remuneracao",
      "prestigio",
      "voce",
      "esta",
      "considerando",
      "iniciar",
      "mudar",
      "carreira",
      "importante",
      "entender",
      "detalhes",
      "dessa",
      "profissao",
      "incluindo",
      "salarios",
      "perspectivas",
      "crescimento",
      "neste",
      "artigo",
      "vamos",
      "explorar",
      "detalhes",
      "significa",
      "auditor",
      "fiscal",
      "quais",
      "requisitos",
      "para",
      "ingressar",
      "nessa",
      "carreira",
      "como",
      "quais",
      "salarios",
      "finalmente",
      "quais",
      "perspectivas",
      "crescimento",
      "desenvolvimento",
      "nessa",
      "area",
      "auditor",
      "fiscal",
      "auditor",
      "fiscal",
      "profissional",
      "responsavel",
      "fiscalizar",
      "auditar",
      "gestao",
      "recursos",
      "publicos",
      "garantindo",
      "leis",
      "regulamentacoes",
      "sejam",
      "seguidas",
      "eles",
      "atuam",
      "diversas",
      "esferas",
      "como",
      "receita",
      "federal",
      "tribunais",
      "contas",
      "secretarias",
      "fazenda",
      "estados",
      "municipios",
      "verificando",
      "correta",
      "aplicacao",
      "recursos",
      "combatendo",
      "sonegacao",
      "evasao",
      "fiscal",
      "outros",
      "ilicitos",
      "contra",
      "ordem",
      "tributaria",
      "alem",
      "disso",
      "auditores",
      "fiscais",
      "desempenham",
      "papel",
      "crucial",
      "arrecadacao",
      "impostos",
      "formulacao",
      "politicas",
      "fiscais",
      "requisitos",
      "para",
      "tornar",
      "auditor",
      "fiscal",
      "para",
      "tornar",
      "auditor",
      "fiscal",
      "necessario",
      "atender",
      "alguns",
      "requisitos",
      "basicos",
      "podem",
      "variar",
      "dependendo",
      "instituicao",
      "para",
      "qual",
      "esta",
      "concorrendo",
      "entanto",
      "alguns",
      "principais",
      "requisitos",
      "incluem",
      "idade",
      "deve",
      "pelo",
      "menos",
      "anos",
      "idade",
      "nacionalidade",
      "deve",
      "brasileiro",
      "caso",
      "estrangeiros",
      "obtido",
      "naturalizacao",
      "escolaridade",
      "deve",
      "possuir"
    ]
  },
  {
    "slug": "carreira-policial-federal-requisitos-e-preparacao",
    "words": [
      "introducao",
      "carreira",
      "policial",
      "federal",
      "mais",
      "respeitadas",
      "desejadas",
      "brasil",
      "oferecendo",
      "oportunidade",
      "servir",
      "nacao",
      "garantir",
      "seguranca",
      "publica",
      "combater",
      "criminalidade",
      "forma",
      "eficaz",
      "entanto",
      "para",
      "ingressar",
      "nessa",
      "carreira",
      "necessario",
      "atender",
      "serie",
      "requisitos",
      "rigorosos",
      "passar",
      "processo",
      "selecao",
      "extremamente",
      "competitivo",
      "neste",
      "artigo",
      "vamos",
      "explorar",
      "requisitos",
      "necessarios",
      "para",
      "tornar",
      "policial",
      "federal",
      "como",
      "estrategias",
      "preparacao",
      "para",
      "aumentar",
      "chances",
      "sucesso",
      "requisitos",
      "para",
      "carreira",
      "policial",
      "federal",
      "idade",
      "nacionalidade",
      "para",
      "candidatar",
      "cargo",
      "policial",
      "federal",
      "necessario",
      "entre",
      "anos",
      "idade",
      "data",
      "inscricao",
      "concurso",
      "alem",
      "disso",
      "candidato",
      "deve",
      "brasileiro",
      "nato",
      "naturalizado",
      "esses",
      "criterios",
      "fundamentais",
      "flexibilidade",
      "relacao",
      "eles",
      "escolaridade",
      "requisito",
      "minimo",
      "escolaridade",
      "para",
      "cargo",
      "policial",
      "federal",
      "nivel",
      "superior",
      "completo",
      "qualquer",
      "area",
      "formacao",
      "isso",
      "significa",
      "candidato",
      "deve",
      "concluido",
      "curso",
      "graduacao",
      "instituicao",
      "ensino",
      "superior",
      "reconhecida",
      "pelo",
      "ministerio",
      "educacao",
      "alem",
      "disso",
      "importante",
      "destacar",
      "area",
      "formacao",
      "fator",
      "limitante",
      "pois",
      "policia",
      "federal",
      "busca",
      "diversidade",
      "habilidades",
      "conhecimentos",
      "exames",
      "medicos",
      "testes",
      "fisicos",
      "alem",
      "requisitos",
      "idade",
      "nacionalidade",
      "escolaridade",
      "candidatos",
      "tambem",
      "precisam",
      "passar",
      "exames",
      "medicos",
      "testes",
      "fisicos",
      "esses",
      "exames",
      "avaliam",
      "saude",
      "capacidade",
      "fisica",
      "candidato"
    ]
  },
  {
    "slug": "como-resolver-questoes-de-raciocinio-logico-em-concursos",
    "words": [
      "raciocinio",
      "logico",
      "habilidades",
      "mais",
      "importantes",
      "desejadas",
      "concursos",
      "publicos",
      "brasil",
      "envolve",
      "capacidade",
      "analisar",
      "informacoes",
      "identificar",
      "padroes",
      "estabelecer",
      "relacoes",
      "logicas",
      "chegar",
      "conclusoes",
      "baseadas",
      "evidencias",
      "contexto",
      "concursos",
      "questoes",
      "raciocinio",
      "logico",
      "projetadas",
      "para",
      "testar",
      "capacidade",
      "candidato",
      "pensar",
      "maneira",
      "critica",
      "logica",
      "sistematica",
      "neste",
      "artigo",
      "vamos",
      "explorar",
      "estrategias",
      "tecnicas",
      "para",
      "resolver",
      "questoes",
      "raciocinio",
      "logico",
      "forma",
      "eficaz",
      "ajudando",
      "candidatos",
      "melhorar",
      "desempenho",
      "concursos",
      "publicos",
      "importancia",
      "raciocinio",
      "logico",
      "antes",
      "mergulharmos",
      "estrategias",
      "para",
      "resolver",
      "questoes",
      "raciocinio",
      "logico",
      "fundamental",
      "entender",
      "essa",
      "habilidade",
      "valorizada",
      "concursos",
      "publicos",
      "capacidade",
      "raciocinar",
      "logicamente",
      "permite",
      "profissionais",
      "tomem",
      "decisoes",
      "informadas",
      "resolvam",
      "problemas",
      "complexos",
      "comuniquem",
      "suas",
      "ideias",
      "maneira",
      "clara",
      "eficaz",
      "contexto",
      "profissional",
      "essas",
      "habilidades",
      "essenciais",
      "para",
      "sucesso",
      "diversas",
      "areas",
      "desde",
      "administracao",
      "publica",
      "gestao",
      "projetos",
      "tomada",
      "decisoes",
      "estrategicas",
      "tipos",
      "questoes",
      "raciocinio",
      "logico",
      "questoes",
      "raciocinio",
      "logico",
      "podem",
      "classificadas",
      "diferentes",
      "tipos",
      "cada",
      "exigindo",
      "conjunto",
      "especifico",
      "habilidades",
      "estrategias",
      "principais",
      "tipos",
      "incluem",
      "logica",
      "dedutiva",
      "envolve",
      "aplicacao",
      "regras",
      "logicas",
      "para",
      "deduzir",
      "conclusoes",
      "partir",
      "premissas",
      "logica",
      "indutiva",
      "requer",
      "capacidade",
      "generalizar",
      "partir",
      "casos",
      "especificos",
      "para",
      "chegar",
      "regra"
    ]
  },
  {
    "slug": "concursos-publicos-com-mais-vagas-para-nivel-medio",
    "words": [
      "introducao",
      "voce",
      "esta",
      "procurando",
      "carreira",
      "estavel",
      "segura",
      "entao",
      "concursos",
      "publicos",
      "excelente",
      "opcao",
      "mais",
      "anos",
      "experiencia",
      "como",
      "professor",
      "mentor",
      "candidatos",
      "aprovados",
      "posso",
      "afirmar",
      "vagas",
      "nivel",
      "medio",
      "porta",
      "entrada",
      "para",
      "muitos",
      "cargos",
      "publicos",
      "neste",
      "artigo",
      "vamos",
      "explorar",
      "oportunidades",
      "concursos",
      "publicos",
      "mais",
      "vagas",
      "para",
      "nivel",
      "medio",
      "fornecer",
      "dicas",
      "praticas",
      "para",
      "ajuda",
      "preparar",
      "aumentar",
      "suas",
      "chances",
      "sucesso",
      "concurso",
      "publicos",
      "importantes",
      "concursos",
      "publicos",
      "processos",
      "seletivos",
      "realizados",
      "orgaos",
      "governamentais",
      "para",
      "preencher",
      "vagas",
      "cargos",
      "publicos",
      "esses",
      "concursos",
      "baseados",
      "criterios",
      "como",
      "conhecimento",
      "habilidades",
      "experiencia",
      "forma",
      "justa",
      "transparente",
      "selecionar",
      "candidatos",
      "para",
      "esses",
      "cargos",
      "vagas",
      "nivel",
      "medio",
      "especialmente",
      "procuradas",
      "pois",
      "muitos",
      "orgaos",
      "governamentais",
      "precisam",
      "profissionais",
      "habilidades",
      "tecnicas",
      "administrativas",
      "para",
      "desempenhar",
      "funcoes",
      "essenciais",
      "areas",
      "mais",
      "vagas",
      "nivel",
      "medio",
      "existem",
      "varias",
      "areas",
      "oferecem",
      "mais",
      "vagas",
      "nivel",
      "medio",
      "concursos",
      "publicos",
      "algumas",
      "principais",
      "incluem",
      "saude",
      "tecnicos",
      "enfermagem",
      "tecnicos",
      "laboratorio",
      "tecnicos",
      "radiologia",
      "entre",
      "outros",
      "educacao",
      "professores",
      "nivel",
      "medio",
      "coordenadores",
      "pedagogicos",
      "orientadores",
      "educacionais",
      "seguranca",
      "agentes",
      "seguranca",
      "guardas",
      "municipais",
      "bombeiros",
      "administracao",
      "assistentes",
      "administrativos",
      "tecnicos",
      "contabilidade",
      "tecnicos",
      "recursos"
    ]
  },
  {
    "slug": "diferencas-entre-editais-estaduais-e-federais",
    "words": [
      "introducao",
      "voce",
      "esta",
      "preparando",
      "para",
      "concursos",
      "publicos",
      "brasil",
      "fundamental",
      "entender",
      "diferencas",
      "entre",
      "editais",
      "estaduais",
      "federais",
      "essas",
      "diferencas",
      "podem",
      "afetar",
      "significativamente",
      "estrategia",
      "estudo",
      "preparacao",
      "alem",
      "influenciar",
      "suas",
      "chances",
      "aprovado",
      "neste",
      "artigo",
      "vamos",
      "explorar",
      "principais",
      "diferencas",
      "entre",
      "esses",
      "dois",
      "tipos",
      "editais",
      "fornecer",
      "dicas",
      "praticas",
      "para",
      "ajuda",
      "preparar",
      "eficacia",
      "caracteristicas",
      "gerais",
      "editais",
      "estaduais",
      "editais",
      "estaduais",
      "publicados",
      "orgaos",
      "entidades",
      "governos",
      "estaduais",
      "para",
      "preencher",
      "vagas",
      "suas",
      "administracoes",
      "esses",
      "editais",
      "podem",
      "variar",
      "significativamente",
      "termos",
      "conteudo",
      "formato",
      "exigencias",
      "dependendo",
      "estado",
      "orgao",
      "publica",
      "entanto",
      "comum",
      "editais",
      "estaduais",
      "tenham",
      "algumas",
      "caracteristicas",
      "comum",
      "como",
      "provas",
      "mais",
      "focadas",
      "conhecimentos",
      "regionais",
      "editais",
      "estaduais",
      "frequentemente",
      "incluem",
      "questoes",
      "avaliam",
      "conhecimento",
      "candidato",
      "sobre",
      "historia",
      "geografia",
      "legislacao",
      "estado",
      "nivel",
      "dificuldade",
      "variado",
      "nivel",
      "dificuldade",
      "provas",
      "pode",
      "variar",
      "dependendo",
      "orgao",
      "cargo",
      "geralmente",
      "considerado",
      "mais",
      "acessivel",
      "editais",
      "federais",
      "menos",
      "concorrentes",
      "comparacao",
      "editais",
      "federais",
      "editais",
      "estaduais",
      "tendem",
      "atrair",
      "menos",
      "candidatos",
      "pode",
      "aumentar",
      "chances",
      "aprovacao",
      "caracteristicas",
      "gerais",
      "editais",
      "federais",
      "editais",
      "federais",
      "publicados",
      "orgaos",
      "entidades",
      "governo",
      "federal",
      "para",
      "preencher",
      "vagas",
      "administracao",
      "esses"
    ]
  },
  {
    "slug": "estrategia-para-questoes-de-portugues-em-concursos-publicos",
    "words": [
      "introducao",
      "voce",
      "esta",
      "preparando",
      "para",
      "concurso",
      "publico",
      "sabe",
      "questoes",
      "portugues",
      "fundamentais",
      "para",
      "sucesso",
      "anos",
      "experiencia",
      "como",
      "professor",
      "mentor",
      "candidatos",
      "aprovados",
      "posso",
      "afirmar",
      "estrategia",
      "certa",
      "pode",
      "fazer",
      "toda",
      "diferenca",
      "neste",
      "artigo",
      "vamos",
      "explorar",
      "melhores",
      "estrategias",
      "para",
      "questoes",
      "portugues",
      "concursos",
      "publicos",
      "desde",
      "compreensao",
      "regras",
      "gramaticais",
      "resolucao",
      "questoes",
      "interpretacao",
      "texto",
      "compreendendo",
      "regras",
      "gramaticais",
      "regras",
      "gramaticais",
      "base",
      "para",
      "resolver",
      "questoes",
      "portugues",
      "concursos",
      "publicos",
      "fundamental",
      "entender",
      "conceitos",
      "morfologia",
      "sintaxe",
      "semantica",
      "morfologia",
      "estuda",
      "estrutura",
      "interna",
      "palavras",
      "enquanto",
      "sintaxe",
      "analisa",
      "organizacao",
      "frases",
      "semantica",
      "ocupa",
      "estudo",
      "significado",
      "palavras",
      "expressoes",
      "compreensao",
      "desses",
      "conceitos",
      "permitira",
      "voce",
      "identifique",
      "corrija",
      "erros",
      "gramaticais",
      "facilidade",
      "analise",
      "texto",
      "interpretacao",
      "analise",
      "texto",
      "interpretacao",
      "habilidades",
      "essenciais",
      "para",
      "resolver",
      "questoes",
      "portugues",
      "concursos",
      "publicos",
      "isso",
      "envolve",
      "entender",
      "contexto",
      "identificar",
      "proposito",
      "texto",
      "alem",
      "reconhecer",
      "relacoes",
      "entre",
      "ideias",
      "apresentadas",
      "texto",
      "voce",
      "deve",
      "perguntar",
      "qual",
      "tema",
      "principal",
      "quem",
      "autor",
      "qual",
      "proposito",
      "quais",
      "principais",
      "ideias",
      "como",
      "elas",
      "relacionam",
      "qual",
      "texto",
      "formal",
      "informal",
      "critico",
      "elogioso",
      "dicas",
      "praticas",
      "para",
      "resolver",
      "questoes",
      "portugues",
      "aqui",
      "estao",
      "dicas"
    ]
  },
  {
    "slug": "melhores-concursos-para-iniciantes-em-2026",
    "words": [
      "introducao",
      "voce",
      "esta",
      "comecando",
      "jornada",
      "concursos",
      "publicos",
      "brasil",
      "fundamental",
      "entender",
      "escolha",
      "concurso",
      "certo",
      "pode",
      "fator",
      "decisivo",
      "para",
      "sucesso",
      "variedade",
      "opcoes",
      "disponiveis",
      "saber",
      "quais",
      "concursos",
      "mais",
      "acessiveis",
      "oferecem",
      "melhores",
      "oportunidades",
      "para",
      "iniciantes",
      "essencial",
      "neste",
      "artigo",
      "vamos",
      "explorar",
      "melhores",
      "concursos",
      "para",
      "iniciantes",
      "destacando",
      "principais",
      "setores",
      "orgaos",
      "costumam",
      "oferecer",
      "vagas",
      "para",
      "aqueles",
      "estao",
      "comecando",
      "carreira",
      "servico",
      "publico",
      "desenvolvimento",
      "concurso",
      "para",
      "agente",
      "administrativo",
      "concursos",
      "mais",
      "procurados",
      "iniciantes",
      "agente",
      "administrativo",
      "este",
      "cargo",
      "encontrado",
      "varias",
      "instituicoes",
      "publicas",
      "como",
      "ministerios",
      "autarquias",
      "empresas",
      "estatais",
      "funcoes",
      "podem",
      "variar",
      "geralmente",
      "incluem",
      "tarefas",
      "administrativas",
      "como",
      "atendimento",
      "publico",
      "gestao",
      "documentos",
      "suporte",
      "processos",
      "internos",
      "requisitos",
      "ensino",
      "medio",
      "completo",
      "dificuldade",
      "considerado",
      "nivel",
      "basico",
      "intermediario",
      "instituicoes",
      "ministerio",
      "educacao",
      "ministerio",
      "saude",
      "entre",
      "outros",
      "concurso",
      "para",
      "tecnico",
      "administrativo",
      "similar",
      "agente",
      "administrativo",
      "tecnico",
      "administrativo",
      "tambem",
      "excelente",
      "opcao",
      "para",
      "iniciantes",
      "entanto",
      "para",
      "este",
      "cargo",
      "necessario",
      "ensino",
      "superior",
      "completo",
      "area",
      "especifica",
      "dependendo",
      "orgao",
      "funcoes",
      "mais",
      "especializadas",
      "podem",
      "incluir",
      "analise",
      "dados",
      "gestao",
      "projetos",
      "desenvolvimento",
      "politicas",
      "administrativas",
      "requisitos",
      "ensino",
      "superior",
      "completo",
      "dificuldade"
    ]
  },
  {
    "slug": "metodo-pomodoro-para-concursos-publicos",
    "words": [
      "introducao",
      "voce",
      "esta",
      "preparando",
      "para",
      "concursos",
      "publicos",
      "busca",
      "estrategia",
      "eficaz",
      "para",
      "gerenciar",
      "tempo",
      "estudo",
      "entao",
      "voce",
      "esta",
      "lugar",
      "certo",
      "anos",
      "experiencia",
      "como",
      "professor",
      "mentor",
      "candidatos",
      "aprovados",
      "posso",
      "afirmar",
      "metodo",
      "pomodoro",
      "ferramenta",
      "poderosa",
      "para",
      "aumentar",
      "produtividade",
      "alcancar",
      "seus",
      "objetivos",
      "neste",
      "artigo",
      "vamos",
      "explorar",
      "como",
      "aplicar",
      "metodo",
      "pomodoro",
      "para",
      "concursos",
      "publicos",
      "como",
      "pode",
      "ajuda",
      "tornar",
      "candidato",
      "mais",
      "eficaz",
      "metodo",
      "pomodoro",
      "metodo",
      "pomodoro",
      "desenvolvido",
      "francesco",
      "cirillo",
      "decada",
      "baseia",
      "tecnica",
      "simples",
      "eficaz",
      "ideia",
      "dividir",
      "tempo",
      "estudo",
      "intervalos",
      "minutos",
      "chamados",
      "pomodoros",
      "separados",
      "pausas",
      "minutos",
      "apos",
      "quatro",
      "pomodoros",
      "voce",
      "pausa",
      "mais",
      "longa",
      "minutos",
      "essa",
      "tecnica",
      "ajuda",
      "manter",
      "foco",
      "evitar",
      "distracao",
      "aumentar",
      "produtividade",
      "aplicando",
      "metodo",
      "pomodoro",
      "concursos",
      "publicos",
      "para",
      "aplicar",
      "metodo",
      "pomodoro",
      "concursos",
      "publicos",
      "voce",
      "precisa",
      "adapta",
      "suas",
      "necessidades",
      "especificas",
      "aqui",
      "estao",
      "algumas",
      "dicas",
      "para",
      "comecar",
      "defina",
      "seus",
      "objetivos",
      "antes",
      "comecar",
      "estudar",
      "defina",
      "voce",
      "quer",
      "alcancar",
      "cada",
      "sessao",
      "estudo",
      "isso",
      "pode",
      "revisar",
      "capitulo",
      "especifico",
      "resolver",
      "conjunto",
      "questoes",
      "praticar",
      "habilidade",
      "crie",
      "cronograma",
      "organize",
      "tempo",
      "estudo",
      "intervalos",
      "minutos",
      "pausas"
    ]
  },
  {
    "slug": "o-que-verificar-antes-de-se-inscrever-em-um-edital",
    "words": [
      "voce",
      "esta",
      "considerando",
      "inscrever",
      "concurso",
      "publico",
      "brasil",
      "fundamental",
      "esteja",
      "preparado",
      "informado",
      "sobre",
      "todos",
      "aspectos",
      "processo",
      "inscricao",
      "concurso",
      "publico",
      "passo",
      "importante",
      "jornada",
      "para",
      "obter",
      "cargo",
      "administracao",
      "publica",
      "crucial",
      "voce",
      "verifique",
      "cuidadosamente",
      "todos",
      "detalhes",
      "antes",
      "esse",
      "passo",
      "neste",
      "artigo",
      "vamos",
      "explorar",
      "voce",
      "precisa",
      "verificar",
      "antes",
      "inscrever",
      "edital",
      "concurso",
      "publico",
      "ajudando",
      "preparar",
      "forma",
      "estrategica",
      "aumentar",
      "suas",
      "chances",
      "sucesso",
      "entendendo",
      "edital",
      "edital",
      "documento",
      "oficial",
      "contem",
      "todas",
      "informacoes",
      "sobre",
      "concurso",
      "publico",
      "publicado",
      "pelo",
      "orgao",
      "responsavel",
      "pelo",
      "concurso",
      "principal",
      "fonte",
      "informacao",
      "para",
      "candidatos",
      "antes",
      "mais",
      "nada",
      "importante",
      "voce",
      "obtenha",
      "copia",
      "edital",
      "leia",
      "atencao",
      "edital",
      "deve",
      "conter",
      "informacoes",
      "detalhadas",
      "sobre",
      "concurso",
      "incluindo",
      "vagas",
      "quantas",
      "vagas",
      "estao",
      "sendo",
      "ofertadas",
      "para",
      "quais",
      "cargos",
      "requisitos",
      "quais",
      "requisitos",
      "minimos",
      "para",
      "inscrever",
      "como",
      "idade",
      "escolaridade",
      "experiencia",
      "prova",
      "informacoes",
      "sobre",
      "tipo",
      "prova",
      "data",
      "hora",
      "local",
      "inscricao",
      "como",
      "quando",
      "inscrever",
      "incluindo",
      "periodo",
      "inscricao",
      "valor",
      "taxa",
      "inscricao",
      "criterios",
      "selecao",
      "como",
      "candidatos",
      "serao",
      "avaliados",
      "selecionados",
      "verificando",
      "requisitos",
      "antes",
      "inscrever",
      "crucial",
      "verificar",
      "voce",
      "atende",
      "todos",
      "requisitos",
      "estabelecidos"
    ]
  },
  {
    "slug": "revisao-espacada-para-memorizar-legislacao",
    "words": [
      "preparacao",
      "para",
      "concursos",
      "publicos",
      "brasil",
      "envolve",
      "vasta",
      "gama",
      "conhecimentos",
      "incluindo",
      "legislacao",
      "especifica",
      "cada",
      "area",
      "legislacao",
      "pilares",
      "fundamentais",
      "para",
      "qualquer",
      "carreira",
      "esfera",
      "publica",
      "pois",
      "fornece",
      "bases",
      "legais",
      "para",
      "acoes",
      "decisoes",
      "tomadas",
      "pelos",
      "servidores",
      "entanto",
      "volume",
      "informacoes",
      "memorizado",
      "pode",
      "esmagador",
      "especialmente",
      "para",
      "aqueles",
      "estao",
      "iniciando",
      "jornada",
      "aqui",
      "entra",
      "tecnica",
      "revisao",
      "espacada",
      "estrategia",
      "comprovada",
      "para",
      "aprimorar",
      "retencao",
      "informacoes",
      "facilitar",
      "processo",
      "memorizacao",
      "neste",
      "artigo",
      "vamos",
      "explorar",
      "detalhes",
      "como",
      "revisao",
      "espacada",
      "pode",
      "aplicada",
      "para",
      "memorizar",
      "legislacao",
      "discutindo",
      "seus",
      "principios",
      "basicos",
      "beneficios",
      "estrategias",
      "praticas",
      "para",
      "implementacao",
      "alem",
      "disso",
      "vamos",
      "abordar",
      "dicas",
      "especificas",
      "para",
      "iniciantes",
      "intermediarios",
      "ajudando",
      "otimizar",
      "estudo",
      "alcancar",
      "melhores",
      "resultados",
      "concursos",
      "publicos",
      "revisao",
      "espacada",
      "revisao",
      "espacada",
      "tecnica",
      "estudo",
      "envolve",
      "revisar",
      "material",
      "estudo",
      "intervalos",
      "tempo",
      "crescentes",
      "ideia",
      "tras",
      "dessa",
      "abordagem",
      "aproveitar",
      "fenomeno",
      "psicologico",
      "conhecido",
      "como",
      "esquecimento",
      "ocorre",
      "naturalmente",
      "quando",
      "tentamos",
      "reter",
      "informacoes",
      "memoria",
      "longo",
      "prazo",
      "revisar",
      "material",
      "intervalos",
      "especificos",
      "voce",
      "ajuda",
      "consolidar",
      "informacoes",
      "memoria",
      "longo",
      "prazo",
      "tornando",
      "mais",
      "facil",
      "lembrar",
      "delas",
      "futuro",
      "beneficios",
      "revisao",
      "espacada",
      "revisao"
    ]
  },
  {
    "slug": "como-montar-cronograma-de-estudos-para-concurso-publico",
    "words": [
      "voce",
      "esta",
      "aqui",
      "porque",
      "esta",
      "preparando",
      "para",
      "concurso",
      "publico",
      "brasil",
      "parabens",
      "pelo",
      "primeiro",
      "passo",
      "montar",
      "cronograma",
      "estudos",
      "eficaz",
      "fundamental",
      "para",
      "alcancar",
      "sucesso",
      "nessa",
      "jornada",
      "neste",
      "artigo",
      "vamos",
      "explorar",
      "como",
      "criar",
      "plano",
      "estudos",
      "personalizado",
      "estrategico",
      "adapte",
      "suas",
      "necessidades",
      "objetivos",
      "antes",
      "comecar",
      "importante",
      "entender",
      "cada",
      "concurso",
      "publico",
      "suas",
      "particularidades",
      "como",
      "tipo",
      "cargo",
      "nivel",
      "dificuldade",
      "conteudo",
      "programatico",
      "portanto",
      "crucial",
      "conhecer",
      "edital",
      "concurso",
      "voce",
      "esta",
      "preparando",
      "alem",
      "disso",
      "fundamental",
      "compreensao",
      "suas",
      "proprias",
      "forcas",
      "fraquezas",
      "como",
      "estilo",
      "aprendizado",
      "conhecendo",
      "edital",
      "edital",
      "concurso",
      "documento",
      "oficial",
      "descreve",
      "todas",
      "regras",
      "requisitos",
      "processo",
      "seletivo",
      "nele",
      "voce",
      "encontrara",
      "informacoes",
      "sobre",
      "cargo",
      "salario",
      "requisitos",
      "inscricao",
      "conteudo",
      "programatico",
      "cronograma",
      "eventos",
      "essencial",
      "edital",
      "atencao",
      "anotar",
      "todas",
      "informacoes",
      "relevantes",
      "algumas",
      "informacoes",
      "mais",
      "importantes",
      "voce",
      "deve",
      "buscar",
      "edital",
      "incluem",
      "conteudo",
      "programatico",
      "quais",
      "disciplinas",
      "assuntos",
      "serao",
      "cobrados",
      "exame",
      "tipo",
      "prova",
      "qual",
      "formato",
      "prova",
      "prova",
      "discursiva",
      "objetiva",
      "combinacao",
      "ambos",
      "duracao",
      "prova",
      "quanto",
      "tempo",
      "voce",
      "tera",
      "para",
      "realizar",
      "prova",
      "data",
      "prova",
      "quando",
      "ocorrera",
      "prova",
      "avaliando",
      "nivel",
      "conhecimento",
      "antes"
    ]
  },
  {
    "slug": "diferencas-entre-editais-estaduais-e-federais",
    "words": [
      "introducao",
      "concursos",
      "publicos",
      "brasil",
      "principais",
      "meios",
      "ingresso",
      "quadros",
      "administracao",
      "publica",
      "seja",
      "ambito",
      "federal",
      "estadual",
      "municipal",
      "para",
      "candidatos",
      "buscam",
      "carreira",
      "estavel",
      "beneficios",
      "atrativos",
      "entender",
      "diferencas",
      "entre",
      "editais",
      "estaduais",
      "federais",
      "fundamental",
      "essa",
      "compreensao",
      "pode",
      "influenciar",
      "significativamente",
      "estrategia",
      "estudo",
      "preparacao",
      "alem",
      "ajudar",
      "candidatos",
      "escolherem",
      "concursos",
      "melhor",
      "adequam",
      "suas",
      "habilidades",
      "objetivos",
      "neste",
      "artigo",
      "vamos",
      "explorar",
      "principais",
      "diferencas",
      "entre",
      "editais",
      "estaduais",
      "federais",
      "abordando",
      "aspectos",
      "como",
      "processo",
      "selecao",
      "requisitos",
      "para",
      "inscricao",
      "disciplinas",
      "avaliadas",
      "duracao",
      "concurso",
      "oportunidades",
      "carreira",
      "alem",
      "disso",
      "vamos",
      "oferecer",
      "dicas",
      "praticas",
      "para",
      "candidatos",
      "estao",
      "iniciando",
      "jornada",
      "concursos",
      "publicos",
      "desenvolvimento",
      "processo",
      "selecao",
      "processos",
      "selecao",
      "para",
      "concursos",
      "estaduais",
      "federais",
      "compartilham",
      "algumas",
      "semelhancas",
      "tambem",
      "apresentam",
      "diferencas",
      "significativas",
      "ambos",
      "casos",
      "processo",
      "geralmente",
      "envolve",
      "provas",
      "escritas",
      "podem",
      "objetivas",
      "discursivas",
      "alguns",
      "casos",
      "provas",
      "praticas",
      "testes",
      "habilidades",
      "especificas",
      "entanto",
      "concursos",
      "federais",
      "tendem",
      "processo",
      "selecao",
      "mais",
      "complexo",
      "rigoroso",
      "maior",
      "variedade",
      "etapas",
      "como",
      "provas",
      "conhecimento",
      "especifico",
      "testes",
      "psicologicos",
      "avaliacoes",
      "titulos",
      "concursos",
      "estaduais",
      "outro",
      "lado",
      "podem",
      "processo",
      "selecao",
      "mais",
      "direto",
      "menos",
      "etapas",
      "menos",
      "desafiador"
    ]
  },
  {
    "slug": "melhores-concursos-para-iniciantes-em-2026",
    "words": [
      "introducao",
      "voce",
      "esta",
      "comecando",
      "preparar",
      "para",
      "concursos",
      "publicos",
      "brasil",
      "fundamental",
      "escolher",
      "certames",
      "mais",
      "adequados",
      "para",
      "nivel",
      "conhecimento",
      "habilidades",
      "neste",
      "artigo",
      "vamos",
      "explorar",
      "melhores",
      "concursos",
      "para",
      "iniciantes",
      "fornecendo",
      "visao",
      "geral",
      "oportunidades",
      "requisitos",
      "estrategias",
      "para",
      "aumentar",
      "suas",
      "chances",
      "sucesso",
      "conursos",
      "publicos",
      "concursos",
      "publicos",
      "processos",
      "seletivos",
      "utilizados",
      "pelo",
      "governo",
      "para",
      "preencher",
      "vagas",
      "orgaos",
      "instituicoes",
      "publicas",
      "esses",
      "concursos",
      "fundamentais",
      "para",
      "garantir",
      "igualdade",
      "oportunidades",
      "meritocracia",
      "acesso",
      "cargos",
      "publicos",
      "para",
      "iniciantes",
      "essencial",
      "entender",
      "cada",
      "concurso",
      "suas",
      "particularidades",
      "como",
      "nivel",
      "dificuldade",
      "tipo",
      "prova",
      "requisitos",
      "especificos",
      "para",
      "cada",
      "cargo",
      "importante",
      "escolher",
      "concurso",
      "certo",
      "escolher",
      "concurso",
      "certo",
      "crucial",
      "para",
      "iniciantes",
      "isso",
      "porque",
      "cada",
      "concurso",
      "nivel",
      "complexidade",
      "conjunto",
      "disciplinas",
      "avaliadas",
      "para",
      "aqueles",
      "estao",
      "comecando",
      "recomendavel",
      "optar",
      "concursos",
      "tenham",
      "nivel",
      "dificuldade",
      "mais",
      "acessivel",
      "exijam",
      "conjunto",
      "conhecimentos",
      "mais",
      "basicos",
      "alem",
      "disso",
      "entender",
      "requisitos",
      "caracteristicas",
      "cada",
      "concurso",
      "ajuda",
      "direcionar",
      "estudos",
      "forma",
      "mais",
      "eficaz",
      "desenvolvimento",
      "concurso",
      "para",
      "agente",
      "policia",
      "federal",
      "nivel",
      "dificuldade",
      "medio",
      "alto",
      "requisitos",
      "nivel",
      "superior",
      "qualquer",
      "area",
      "carteira",
      "habilitacao",
      "categoria",
      "superior",
      "disciplinas"
    ]
  }
]